torchtostr/__init__.py
torchtostr/torchtostr.py
torchtostr-1.2.dist-info/LICENSE
torchtostr-1.2.dist-info/METADATA
torchtostr-1.2.dist-info/WHEEL
torchtostr-1.2.dist-info/top_level.txt
torchtostr-1.2.dist-info/RECORD
