Metadata-Version: 2.1
Name: torchtostr
Version: 1.2
Summary: Module for quick and simple transportation of torch tensors arrays by converting them to str and back
Author: ankov
Project-URL: GitHub, https://github.com/Ankov404/torchtostr
Keywords: tensors strings torch pytorch
Classifier: Programming Language :: Python :: 3.11
Classifier: License :: OSI Approved :: MIT License
Classifier: Operating System :: OS Independent
License-File: LICENSE
Requires-Dist: torch
Requires-Dist: torchvision
Requires-Dist: torchaudio
Requires-Dist: numpy
